phringe/__init__.py
phringe/core/__init__.py
phringe/core/base_entity.py
phringe/core/configuration.py
phringe/core/instrument.py
phringe/core/observation.py
phringe/core/perturbations/__init__.py
phringe/core/perturbations/base_perturbation.py
phringe/core/perturbations/power_law_psd_perturbation.py
phringe/core/scene.py
phringe/core/sources/__init__.py
phringe/core/sources/base_source.py
phringe/core/sources/exozodi.py
phringe/core/sources/local_zodi.py
phringe/core/sources/planet.py
phringe/core/sources/star.py
phringe/io/__init__.py
phringe/io/input_spectrum.py
phringe/io/nifits_writer.py
phringe/io/validation.py
phringe/lib/__init__.py
phringe/lib/array_architecture.py
phringe/lib/array_configuration.py
phringe/lib/beam_combiner.py
phringe/main.py
phringe/util/__init__.py
phringe/util/baseline.py
phringe/util/device.py
phringe/util/grid.py
phringe/util/installation.py
phringe/util/spectrum.py
phringe-1.5.5.dist-info/METADATA
phringe-1.5.5.dist-info/WHEEL
phringe-1.5.5.dist-info/licenses/LICENSE
phringe-1.5.5.dist-info/RECORD
