Metadata-Version: 2.4
Name: phringe
Version: 1.5.5
Summary: PHRINGE
License: MIT
License-File: LICENSE
Author: Philipp A. Huber
Author-email: huberph@phys.ethz.ch
Requires-Python: >=3.10
Classifier: Development Status :: 4 - Beta
Classifier: License :: OSI Approved :: MIT License
Classifier: Programming Language :: Python :: 3
Classifier: Programming Language :: Python :: 3.10
Classifier: Programming Language :: Python :: 3.11
Classifier: Programming Language :: Python :: 3.12
Classifier: Programming Language :: Python :: 3.13
Classifier: Programming Language :: Python :: 3.14
Requires-Dist: astropy (>=5.3,<6)
Requires-Dist: myst-nb (>=1.2.0,<2.0.0)
Requires-Dist: numpy (>=1.26.3,<2.0.0)
Requires-Dist: poliastro (==0.7.0)
Requires-Dist: psutil (>=6.1.1,<7.0.0)
Requires-Dist: pydantic (>=2.6.1,<3.0.0)
Requires-Dist: scikit-image (>=0.23.2,<0.24.0)
Requires-Dist: spectres (>=2.2.0,<3.0.0)
Requires-Dist: sphinx-copybutton (>=0.5.2)
Requires-Dist: sympy (>=1.13.3,<2.0.0)
Requires-Dist: torch (>=1.13.0)
Requires-Dist: tqdm (>=4.66.1,<5.0.0)
Project-URL: Changelog, https://github.com/pahuber/phringe/releases
Project-URL: Documentation, https://phringe.readthedocs.io
Project-URL: Homepage, https://github.com/pahuber/phringe
Project-URL: Repository, https://github.com/pahuber/phringe
